MANIFEST.in
README.rst
requirements.txt
setup.py
nekumo/__init__.py
nekumo/exceptions.py
nekumo/models.py
nekumo.egg-info/PKG-INFO
nekumo.egg-info/SOURCES.txt
nekumo.egg-info/dependency_links.txt
nekumo.egg-info/not-zip-safe
nekumo.egg-info/pbr.json
nekumo.egg-info/requires.txt
nekumo.egg-info/top_level.txt
nekumo/conf/__init__.py
nekumo/conf/base.py
nekumo/core/__init__.py
nekumo/core/api.py
nekumo/core/events.py
nekumo/core/i18n.py
nekumo/core/management.py
nekumo/core/nekumo.py
nekumo/core/pubsub.py
nekumo/gateways/__init__.py
nekumo/gateways/base.py
nekumo/gateways/fs/__init__.py
nekumo/gateways/fs/watcher.py
nekumo/ifaces/__init__.py
nekumo/ifaces/base.py
nekumo/ifaces/angular_web/__init__.py
nekumo/ifaces/angular_web/api.py
nekumo/ifaces/angular_web/events.py
nekumo/ifaces/angular_web/views.py
nekumo/ifaces/angular_web/static/dist/audioPlayer.js
nekumo/ifaces/angular_web/static/dist/common.css
nekumo/ifaces/angular_web/static/dist/common.js
nekumo/ifaces/angular_web/static/dist/fileManager.css
nekumo/ifaces/angular_web/static/dist/fileManager.js
nekumo/ifaces/angular_web/static/dist/materialdesignicons-webfont.eot
nekumo/ifaces/angular_web/static/dist/materialdesignicons-webfont.svg
nekumo/ifaces/angular_web/static/dist/materialdesignicons-webfont.ttf
nekumo/ifaces/angular_web/static/dist/materialdesignicons-webfont.woff
nekumo/ifaces/angular_web/static/dist/materialdesignicons-webfont.woff2
nekumo/ifaces/angular_web/static/dist/media.css
nekumo/ifaces/angular_web/static/dist/media.js
nekumo/ifaces/angular_web/static/dist/system-build.js
nekumo/ifaces/angular_web/static/dist/system-csp-production.js
nekumo/ifaces/angular_web/static/dist/system.js
nekumo/ifaces/angular_web/static/dist/videoPlayer.css
nekumo/ifaces/angular_web/static/dist/videoPlayer.js
nekumo/ifaces/angular_web/templates/base.html
nekumo/ifaces/angular_web/templates/fileManager.html
nekumo/ifaces/angular_web/templates/list.html
nekumo/ifaces/angular_web/templates/media.html
nekumo/ifaces/simple_web/__init__.py
nekumo/ifaces/simple_web/api.py
nekumo/ifaces/simple_web/exceptions.py
nekumo/ifaces/simple_web/jinja.py
nekumo/ifaces/simple_web/views.py
nekumo/ifaces/simple_web/templates/base.html
