Metadata-Version: 1.1
Name: nekumo
Version: 0.1.1
Summary: Package description
